d1_common/__init__.py
d1_common/bagit.py
d1_common/checksum.py
d1_common/const.py
d1_common/date_time.py
d1_common/env.py
d1_common/logging_context.py
d1_common/multipart.py
d1_common/node.py
d1_common/object_format_cache.json
d1_common/object_format_cache.py
d1_common/replication_policy.py
d1_common/resource_map.py
d1_common/revision.py
d1_common/system_metadata.py
d1_common/type_conversions.py
d1_common/typing.py
d1_common/url.py
d1_common/util.py
d1_common/xml.py
d1_common/cert/__init__.py
d1_common/cert/jwt.py
d1_common/cert/subject_info.py
d1_common/cert/subject_info_renderer.py
d1_common/cert/subjects.py
d1_common/cert/view_subject_info.py
d1_common/cert/x509.py
d1_common/ext/__init__.py
d1_common/ext/mimeparser.py
d1_common/iter/__init__.py
d1_common/iter/bytes.py
d1_common/iter/path.py
d1_common/iter/stream.py
d1_common/iter/string.py
d1_common/tests/__init__.py
d1_common/tests/test_checksum.py
d1_common/tests/test_date_time.py
d1_common/tests/test_exceptions.py
d1_common/tests/test_file_iterator.py
d1_common/tests/test_jwt.py
d1_common/tests/test_logrecords.py
d1_common/tests/test_multipart.py
d1_common/tests/test_nodelist.py
d1_common/tests/test_object_format_cache.py
d1_common/tests/test_objectlist.py
d1_common/tests/test_objectlocationlist.py
d1_common/tests/test_pid.py
d1_common/tests/test_replication_policy.py
d1_common/tests/test_resource_map.py
d1_common/tests/test_subject_info.py
d1_common/tests/test_subject_info_renderer.py
d1_common/tests/test_system_metadata.py
d1_common/tests/test_type_conversions.py
d1_common/tests/test_url.py
d1_common/tests/test_util.py
d1_common/tests/test_wrap_access_policy.py
d1_common/tests/test_wrap_simple_xml.py
d1_common/tests/test_x509.py
d1_common/tests/test_xml.py
d1_common/types/__init__.py
d1_common/types/dataoneErrors.py
d1_common/types/dataoneTypes.py
d1_common/types/dataoneTypes_v1.py
d1_common/types/dataoneTypes_v1_1.py
d1_common/types/dataoneTypes_v1_2.py
d1_common/types/dataoneTypes_v2_0.py
dataone.common-3.5.2.dist-info/METADATA
dataone.common-3.5.2.dist-info/WHEEL
dataone.common-3.5.2.dist-info/top_level.txt
dataone.common-3.5.2.dist-info/RECORD
